littlenn/__init__.py
littlenn/activation_functions/__init__.py
littlenn/activation_functions/abstract_activation.py
littlenn/activation_functions/linear.py
littlenn/activation_functions/relu.py
littlenn/activation_functions/sigmoid.py
littlenn/layers/__init__.py
littlenn/layers/abstract_layer.py
littlenn/layers/batch_norm.py
littlenn/layers/conv2d.py
littlenn/layers/dense.py
littlenn/layers/dropout.py
littlenn/layers/flatten.py
littlenn/losses/__init__.py
littlenn/losses/binary_crossentropy.py
littlenn/losses/categorical_crossentropy_with_logits.py
littlenn/metrics/__init__.py
littlenn/metrics/binary_accuracy.py
littlenn/metrics/categorical_accuracy.py
littlenn/model/__init__.py
littlenn/model/abstract_model.py
littlenn/model/model.py
littlenn/optimizers/__init__.py
littlenn/optimizers/adam.py
littlenn/optimizers/adam_factory.py
littlenn/optimizers/rmsprop.py
littlenn/optimizers/rmsprop_factory.py
littlenn/optimizers/sgd.py
littlenn/optimizers/sgd_factory.py
tests/__init__.py
tests/training.py
tests/training_conv.py
tests/training_softmax.py
tests/model/__init__.py
tests/model/test_model.py
littlenn-0.0.3.dist-info/LICENSE
littlenn-0.0.3.dist-info/METADATA
littlenn-0.0.3.dist-info/WHEEL
littlenn-0.0.3.dist-info/top_level.txt
littlenn-0.0.3.dist-info/RECORD
